odoo/addons/l10n_th_vat_report/README.rst
odoo/addons/l10n_th_vat_report/__init__.py
odoo/addons/l10n_th_vat_report/__manifest__.py
odoo/addons/l10n_th_vat_report/data/paper_format.xml
odoo/addons/l10n_th_vat_report/data/report_data.xml
odoo/addons/l10n_th_vat_report/i18n/l10n_th_vat_report.pot
odoo/addons/l10n_th_vat_report/readme/CONTRIBUTORS.rst
odoo/addons/l10n_th_vat_report/readme/DESCRIPTION.rst
odoo/addons/l10n_th_vat_report/readme/HISTORY.rst
odoo/addons/l10n_th_vat_report/readme/USAGE.rst
odoo/addons/l10n_th_vat_report/reports/__init__.py
odoo/addons/l10n_th_vat_report/reports/vat_report.py
odoo/addons/l10n_th_vat_report/reports/vat_report.xml
odoo/addons/l10n_th_vat_report/reports/vat_report_xlsx.py
odoo/addons/l10n_th_vat_report/static/description/icon.png
odoo/addons/l10n_th_vat_report/static/description/index.html
odoo/addons/l10n_th_vat_report/static/src/css/report.css
odoo/addons/l10n_th_vat_report/static/src/js/l10n_th_vat_report_backend.js
odoo/addons/l10n_th_vat_report/tests/__init__.py
odoo/addons/l10n_th_vat_report/tests/test_vat_report.py
odoo/addons/l10n_th_vat_report/wizard/__init__.py
odoo/addons/l10n_th_vat_report/wizard/vat_report_wizard.py
odoo/addons/l10n_th_vat_report/wizard/vat_report_wizard_view.xml
odoo12_addon_l10n_th_vat_report-12.0.1.1.1.dist-info/METADATA
odoo12_addon_l10n_th_vat_report-12.0.1.1.1.dist-info/WHEEL
odoo12_addon_l10n_th_vat_report-12.0.1.1.1.dist-info/top_level.txt
odoo12_addon_l10n_th_vat_report-12.0.1.1.1.dist-info/RECORD
