Metadata-Version: 2.1
Name: odoo12-addon-l10n-th-vat-report
Version: 12.0.1.1.1
Summary: Thailand Localization - VAT Reports
Home-page: https://github.com/OCA/l10n-thailand
Author: Ecosoft, Odoo Community Association (OCA)
Author-email: support@odoo-community.org
License: AGPL-3
Platform: UNKNOWN
Classifier: Programming Language :: Python
Classifier: Framework :: Odoo
Classifier: License :: OSI Approved :: GNU Affero General Public License v3
Requires-Python: >=3.5
Requires-Dist: odoo12-addon-date-range
Requires-Dist: odoo12-addon-l10n-th-partner
Requires-Dist: odoo12-addon-l10n-th-vendor-tax-invoice
Requires-Dist: odoo12-addon-report-xlsx-helper
Requires-Dist: odoo (<12.1dev,>=12.0a)
